hses_genesis/__init__.py
hses_genesis/__main__.py
hses_genesis/generation/__init__.py
hses_genesis/generation/communication.py
hses_genesis/generation/dynamic_configuration.py
hses_genesis/generation/network_configuration.py
hses_genesis/generation/topology.py
hses_genesis/parsing/__init__.py
hses_genesis/parsing/configuration.py
hses_genesis/parsing/ruleset.py
hses_genesis/reload/__init__.py
hses_genesis/reload/packets.py
hses_genesis/reload/ruleset.py
hses_genesis/reload/topology.py
hses_genesis/resources/__init__.py
hses_genesis/resources/configurations/EPIC_config.json
hses_genesis/resources/configurations/SWaT_config.json
hses_genesis/resources/configurations/__init__.py
hses_genesis/resources/configurations/configuration_hints.json
hses_genesis/resources/configurations/example_config.json
hses_genesis/resources/configurations/iterating_example_config.json
hses_genesis/resources/configurations/next_generation_config.json
hses_genesis/resources/templates/__init__.py
hses_genesis/resources/templates/omnetpp.ini
hses_genesis/resources/templates/template.cc
hses_genesis/resources/templates/template.ned
hses_genesis/save/__init__.py
hses_genesis/save/packets.py
hses_genesis/save/rulesets.py
hses_genesis/save/topology.py
hses_genesis/setup/__init__.py
hses_genesis/setup/output_location.py
hses_genesis/utils/__init__.py
hses_genesis/utils/constants.py
hses_genesis/utils/enum_objects.py
hses_genesis/utils/functions.py
hses_genesis-1.2.dist-info/METADATA
hses_genesis-1.2.dist-info/WHEEL
hses_genesis-1.2.dist-info/RECORD
