Metadata-Version: 2.4
Name: hses_genesis
Version: 1.2
Summary: GeNESIS - Generator for Network Evaluation Scenarios of Industrial Systems
Project-URL: Homepage, https://github.com/hs-esslingen-it-security/hses-GeNESIS
Author-email: Samuel Mueller <samuel.mueller@hs-esslingen.de>, Lukas Bechtel <lukas.bechtel@hs-esslingen.de>, Lukas Popperl <lukas.popperl@hs-esslingen.de>
License-Expression: MIT
Classifier: Operating System :: OS Independent
Classifier: Programming Language :: Python :: 3
Requires-Python: >=3.8
Requires-Dist: matplotlib
Requires-Dist: networkx
Requires-Dist: scipy
